src/__init__.py
src/main.py
src/analysis/__init__.py
src/analysis/analyzer.py
src/analysis/metrics.py
src/analysis/prompts.py
src/config/__init__.py
src/config/settings.py
src/generation/__init__.py
src/generation/content_generator.py
src/generation/quality_control.py
src/generation/style_transfer.py
src/generation/templates.py
src/menu/__init__.py
src/menu/main_menu.py
src/menu/model_selection.py
src/menu/navigation.py
src/models/__init__.py
src/models/gemini_client.py
src/models/ollama_client.py
src/models/openai_client.py
src/storage/__init__.py
src/storage/local_storage.py
src/utils/__init__.py
src/utils/formatters.py
src/utils/text_processing.py
src/utils/user_profile.py
style_transfer_ai-1.2.0.data/data/check_config.py
style_transfer_ai-1.2.0.dist-info/licenses/LICENSE
style_transfer_ai-1.2.0.dist-info/METADATA
style_transfer_ai-1.2.0.dist-info/WHEEL
style_transfer_ai-1.2.0.dist-info/entry_points.txt
style_transfer_ai-1.2.0.dist-info/top_level.txt
style_transfer_ai-1.2.0.dist-info/RECORD
