Metadata-Version: 2.4
Name: style-transfer-ai
Version: 1.2.0
Summary: Advanced stylometry analysis system with modular architecture
Home-page: https://github.com/alwynrejicser/style-transfer-ai
Download-URL: https://github.com/alwynrejicser/style-transfer-ai/archive/v1.0.0.tar.gz
Author: Alwyn Rejicser
Author-email: alwynrejicser@gmail.com
License: MIT
Project-URL: Documentation, https://github.com/alwynrejicser/style-transfer-ai/wiki
Project-URL: Source, https://github.com/alwynrejicser/style-transfer-ai
Project-URL: Tracker, https://github.com/alwynrejicser/style-transfer-ai/issues
Keywords: stylometry,text analysis,writing style,natural language processing,AI
Classifier: Development Status :: 5 - Production/Stable
Classifier: Intended Audience :: Developers
Classifier: Intended Audience :: Science/Research
Classifier: License :: OSI Approved :: MIT License
Classifier: Programming Language :: Python :: 3
Classifier: Programming Language :: Python :: 3.7
Classifier: Programming Language :: Python :: 3.8
Classifier: Programming Language :: Python :: 3.9
Classifier: Programming Language :: Python :: 3.10
Classifier: Programming Language :: Python :: 3.11
Classifier: Topic :: Scientific/Engineering :: Artificial Intelligence
Classifier: Topic :: Text Processing :: Linguistic
Requires-Python: >=3.7
License-File: LICENSE
Requires-Dist: requests>=2.25.0
Provides-Extra: openai
Requires-Dist: openai>=1.0.0; extra == "openai"
Provides-Extra: gemini
Requires-Dist: google-generativeai; extra == "gemini"
Provides-Extra: all
Requires-Dist: openai>=1.0.0; extra == "all"
Requires-Dist: google-generativeai; extra == "all"
Dynamic: author
Dynamic: author-email
Dynamic: classifier
Dynamic: description
Dynamic: description-content-type
Dynamic: download-url
Dynamic: home-page
Dynamic: keywords
Dynamic: license
Dynamic: license-file
Dynamic: project-url
Dynamic: provides-extra
Dynamic: requires-dist
Dynamic: requires-python
Dynamic: summary
